ohmypika/__init__.py
ohmypika-0.1.0.dist-info/LICENSE
ohmypika-0.1.0.dist-info/WHEEL
ohmypika-0.1.0.dist-info/METADATA
ohmypika-0.1.0.dist-info/RECORD
