Metadata-Version: 2.1
Name: ohmypika
Version: 0.1.0
Summary: oh-my-pika is not an ORM, but it can give Python developers a better SQL writing experience
Home-page: https://github.com/so1n/oh-my-pika
License: Apache Software License
Author: so1n
Author-email: qaz6803609@163.com
Requires-Python: >=3.7,<4.0
Classifier: License :: Other/Proprietary License
Classifier: Programming Language :: Python :: 3
Classifier: Programming Language :: Python :: 3.10
Classifier: Programming Language :: Python :: 3.7
Classifier: Programming Language :: Python :: 3.8
Classifier: Programming Language :: Python :: 3.9
Requires-Dist: PyPika (>=0.48.9,<0.49.0)
Requires-Dist: omymodels (>=0.11.0,<0.12.0)
Project-URL: Repository, https://github.com/so1n/oh-my-pika
